polychemprint3/__init__.py
polychemprint3/__main__.py
polychemprint3/axes/__init__.py
polychemprint3/axes/axes3DSpec.py
polychemprint3/axes/lulzbotTaz6_BP.py
polychemprint3/axes/nullAxes.py
polychemprint3/commandLineInterface/__init__.py
polychemprint3/commandLineInterface/ioElementSpec.py
polychemprint3/commandLineInterface/ioMenuSpec.py
polychemprint3/commandLineInterface/ioTextPanel.py
polychemprint3/data/__init__.py
polychemprint3/data/TextPanels/LICENSE.txt
polychemprint3/data/TextPanels/__init__.py
polychemprint3/recipes/__init__.py
polychemprint3/recipes/recipe.py
polychemprint3/sequence/GCodeFile3DSlicer.py
polychemprint3/sequence/GCodeFileInkscape.py
polychemprint3/sequence/__init__.py
polychemprint3/sequence/basicMove.py
polychemprint3/sequence/circle.py
polychemprint3/sequence/cuboid.py
polychemprint3/sequence/gapLine.py
polychemprint3/sequence/line.py
polychemprint3/sequence/pause.py
polychemprint3/sequence/plate.py
polychemprint3/sequence/pyramid.py
polychemprint3/sequence/rectangle.py
polychemprint3/sequence/sequenceSpec.py
polychemprint3/sequence/setToolState.py
polychemprint3/sequence/triangle.py
polychemprint3/tools/__init__.py
polychemprint3/tools/laser6W.py
polychemprint3/tools/nullTool.py
polychemprint3/tools/toolSpec.py
polychemprint3/tools/ultimusExtruder.py
polychemprint3/user/__init__.py
polychemprint3/user/user.py
polychemprint3/utility/__init__.py
polychemprint3/utility/fileHandler.py
polychemprint3/utility/loggerSpec.py
polychemprint3/utility/serialDeviceSpec.py
polychemprint3_beta-0.0.10.dist-info/LICENSE.txt
polychemprint3_beta-0.0.10.dist-info/METADATA
polychemprint3_beta-0.0.10.dist-info/WHEEL
polychemprint3_beta-0.0.10.dist-info/entry_points.txt
polychemprint3_beta-0.0.10.dist-info/top_level.txt
polychemprint3_beta-0.0.10.dist-info/RECORD
