Metadata-Version: 2.1
Name: polychemprint3-beta
Version: 0.0.10
Summary: FOSS additive manufacturing control software targeted at research Users (Polymer/Paste/BioPrinting) 
Home-page: https://github.com/BijalBPatel/PolyChemPrint3/tree/beta
Author: Bijal Patel
Author-email: bbpatel2@illinois.edu
License: UNKNOWN
Project-URL: Bug Reports, https://github.com/BijalBPatel/PolyChemPrint3/issues
Project-URL: Documentation, https://polychemprint3.readthedocs.io
Project-URL: Source, https://github.com/BijalBPatel/PolyChemPrint3/tree/beta
Keywords: 3D Printing Additive Manufacturing
Platform: UNKNOWN
Classifier: Development Status :: 4 - Beta
Classifier: Intended Audience :: Science/Research
Classifier: Topic :: Scientific/Engineering
Classifier: License :: OSI Approved :: University of Illinois/NCSA Open Source License
Classifier: Programming Language :: Python :: 3.7
Requires-Python: >= 3, <3.8
Requires-Dist: pyserial
Requires-Dist: colorama
Requires-Dist: pyyaml
Requires-Dist: psutil
Requires-Dist: babel
Requires-Dist: pillow
Requires-Dist: tkfilebrowser
Requires-Dist: pywin32 (>=1.0) ; sys_platform == "win32"
